font_intuitive/__init__.py
font_intuitive/files/Intuitive.ttf
font_intuitive/files/OFL.txt
font_intuitive-0.0.4.dist-info/DESCRIPTION.rst
font_intuitive-0.0.4.dist-info/METADATA
font_intuitive-0.0.4.dist-info/RECORD
font_intuitive-0.0.4.dist-info/WHEEL
font_intuitive-0.0.4.dist-info/entry_points.txt
font_intuitive-0.0.4.dist-info/metadata.json
font_intuitive-0.0.4.dist-info/top_level.txt
